drax_ecc/__init__.py
drax_ecc/crypto.py
drax_ecc/darwin/x64/libcrypto.dylib
drax_ecc/unix/x64/libcrypto.so
drax_ecc/win/x64/libcrypto.dll
drax_ecc-1.0.7.dist-info/LICENSE
drax_ecc-1.0.7.dist-info/METADATA
drax_ecc-1.0.7.dist-info/WHEEL
drax_ecc-1.0.7.dist-info/RECORD
