Metadata-Version: 2.1
Name: drax-ecc
Version: 1.0.7
Summary: ECDH Crypto library for Drax
Author: Applica Software Guru
Author-email: info@applica.guru
Requires-Python: >=3.10,<4.0
Classifier: Programming Language :: Python :: 3
Classifier: Programming Language :: Python :: 3.10
Classifier: Programming Language :: Python :: 3.11
Classifier: Programming Language :: Python :: 3.12
Classifier: Programming Language :: Python :: 3.13
Requires-Dist: numpy (>=1.26.4,<2.0.0)
